maha/__init__.py
maha/cleaners/__init__.py
maha/cleaners/functions/__init__.py
maha/cleaners/functions/contains_fn.py
maha/cleaners/functions/keep_fn.py
maha/cleaners/functions/normalize_fn.py
maha/cleaners/functions/num2text.py
maha/cleaners/functions/remove_fn.py
maha/cleaners/functions/replace_fn.py
maha/cleaners/pipelines.py
maha/constants/__init__.py
maha/constants/arabic/__init__.py
maha/constants/arabic/compound.py
maha/constants/arabic/simple.py
maha/constants/english/__init__.py
maha/constants/english/compound.py
maha/constants/english/simple.py
maha/constants/general.py
maha/constants/persian/__init__.py
maha/constants/persian/compound.py
maha/constants/persian/simple.py
maha/deprecation.py
maha/expressions/__init__.py
maha/expressions/arabic.py
maha/expressions/english.py
maha/expressions/general.py
maha/parsers/__init__.py
maha/parsers/functions/__init__.py
maha/parsers/functions/parse_dimensions.py
maha/parsers/functions/parse_fn.py
maha/parsers/rules/__init__.py
maha/parsers/rules/common.py
maha/parsers/rules/duration/__init__.py
maha/parsers/rules/duration/rule.py
maha/parsers/rules/duration/template.py
maha/parsers/rules/duration/utils.py
maha/parsers/rules/duration/values.py
maha/parsers/rules/names.py
maha/parsers/rules/numeral/__init__.py
maha/parsers/rules/numeral/rule.py
maha/parsers/rules/numeral/values.py
maha/parsers/rules/ordinal/__init__.py
maha/parsers/rules/ordinal/rule.py
maha/parsers/rules/ordinal/values.py
maha/parsers/rules/time/__init__.py
maha/parsers/rules/time/constants.py
maha/parsers/rules/time/rule.py
maha/parsers/rules/time/template.py
maha/parsers/rules/time/values.py
maha/parsers/templates/__init__.py
maha/parsers/templates/dimension.py
maha/parsers/templates/enums.py
maha/parsers/templates/text_expression.py
maha/parsers/templates/value_expressions.py
maha/parsers/utils.py
maha/processors/__init__.py
maha/processors/base_processor.py
maha/processors/basic_processors.py
maha/processors/stream_processors.py
mahad-0.3.0.dist-info/LICENSE
mahad-0.3.0.dist-info/WHEEL
mahad-0.3.0.dist-info/METADATA
mahad-0.3.0.dist-info/RECORD
