Metadata-Version: 2.1
Name: mahad
Version: 0.3.0
Summary: An Arabic text processing library intended for use in NLP applications.
Home-page: https://github.com/TRoboto/Maha
License: BSD-3-Clause
Keywords: Arabic,NLP,Text Processing,Parsers,Stream Text Processing
Author: Mohammad Al-Fetyani
Author-email: m4bh@hotmail.com
Requires-Python: >=3.7.1,<4.0.0
Classifier: Development Status :: 4 - Beta
Classifier: License :: OSI Approved :: BSD License
Classifier: Natural Language :: Arabic
Classifier: Natural Language :: English
Classifier: Programming Language :: Python :: 3
Classifier: Programming Language :: Python :: 3.10
Classifier: Programming Language :: Python :: 3.7
Classifier: Programming Language :: Python :: 3.8
Classifier: Programming Language :: Python :: 3.9
Classifier: Topic :: Scientific/Engineering
Classifier: Topic :: Text Processing
Classifier: Topic :: Utilities
Requires-Dist: hijri-converter (>=2.2.3,<3.0.0)
Requires-Dist: python-dateutil (>=2.8.2,<3.0.0)
Requires-Dist: regex (>=2021.8.28,<2022.0.0)
Requires-Dist: tqdm (>=4.61.1,<5.0.0)
Requires-Dist: typing-extensions (>=3.10.0,<4.0.0)
Project-URL: Bug Tracker, https://github.com/TRoboto/Maha/issues
Project-URL: Documentation, https://maha.readthedocs.io
Project-URL: Discord, https://discord.gg/6W2tRFE7k4
Project-URL: Repository, https://github.com/TRoboto/Maha
